{
    "roles": ["admin", "user"],
    "permissions": {
        "config": {
            "access-config": [],
            "access-ui-config": [],
            "enable-login": ["user"]
        },
        "utility": {
            "access-todo": ["user"]
        },
        "site": {
            "access-page": [],
            "access-page-config": [],
            "list-query": ["user"],
            "response-query": [],
            "delete-query": [],
            "list-subscriber": ["user"],
            "delete-subscriber": []
        },
        "user": {
            "list-user": ["user"],
            "create-user": [],
            "edit-user": [],
            "delete-user": []
        },
        "entities": {
            "access-entity": ["admin"]
        }
    }
}